{
  "id": "architecture/collaboration",
  "title": "@barocss/collaboration",
  "description": "Core interfaces and base adapter for connecting Barocss DataStore to CRDT/OT backends. All concrete adapters (Yjs, Liveblocks) extend this package.",
  "source": "@site/docs/architecture/collaboration.md",
  "sourceDirName": "architecture",
  "slug": "/architecture/collaboration",
  "permalink": "/docs/architecture/collaboration",
  "draft": false,
  "unlisted": false,
  "editUrl": "https://github.com/barocss/barocss-editor/tree/main/apps/docs-site/docs/architecture/collaboration.md",
  "tags": [],
  "version": "current",
  "frontMatter": {
    "title": "@barocss/collaboration",
    "sidebar_label": "@barocss/collaboration"
  },
  "sidebar": "tutorialSidebar",
  "previous": {
    "title": "@barocss/text-analyzer",
    "permalink": "/docs/architecture/text-analyzer"
  },
  "next": {
    "title": "@barocss/collaboration-yjs",
    "permalink": "/docs/architecture/collaboration-yjs"
  }
}